upsilon_workshop_client/__init__.py
upsilon_workshop_client/__main__.py
upsilon_workshop_client/api/__init__.py
upsilon_workshop_client/api/project.py
upsilon_workshop_client/api/search.py
upsilon_workshop_client/cli/__init__.py
upsilon_workshop_client/cli/calculator.py
upsilon_workshop_client/cli/parse.py
upsilon_workshop_client/cli/simulator.py
upsilon_workshop_client/cli/workshop.py
upsilon_workshop_client/utils/__init__.py
upsilon_workshop_client/utils/calculator/__init__.py
upsilon_workshop_client/utils/calculator/backup.py
upsilon_workshop_client/utils/calculator/upload.py
upsilon_workshop_client/utils/clone.py
upsilon_workshop_client/utils/init.py
upsilon_workshop_client/utils/pull.py
upsilon_workshop_client/utils/push.py
upsilon_workshop_client/utils/search.py
upsilon_workshop_client/utils/simulator/__init__.py
upsilon_workshop_client/utils/simulator/run.py
upsilon_workshop_client-1.0.1.dist-info/METADATA
upsilon_workshop_client-1.0.1.dist-info/WHEEL
upsilon_workshop_client-1.0.1.dist-info/entry_points.txt
upsilon_workshop_client-1.0.1.dist-info/RECORD
