Metadata-Version: 2.1
Name: upsilon-workshop-client
Version: 1.0.1
Summary: A CLI client for the Upsilon Workshop
Author: Yaya-Cout
Author-email: yaya.cout@ik.me
Requires-Python: >=3.6,<4.0
Classifier: Programming Language :: Python :: 3
Classifier: Programming Language :: Python :: 3.6
Classifier: Programming Language :: Python :: 3.7
Classifier: Programming Language :: Python :: 3.8
Classifier: Programming Language :: Python :: 3.9
Classifier: Programming Language :: Python :: 3.10
Classifier: Programming Language :: Python :: 3.11
Requires-Dist: requests (>=2.28.1,<3.0.0)
Requires-Dist: rich (>=13.0.1,<14.0.0)
Requires-Dist: typer (>=0.7.0,<0.8.0)
Requires-Dist: upsilon-py (>=1.0.0,<2.0.0)
